univer_use/__init__.py
univer_use/artifact_aware_tool.py
univer_use/graph.py
univer_use/model.py
univer_use/py.typed
univer_use/spreadsheet_act.py
univer_use/state.py
univer_use/tools.py
univer_use/prompts/__init__.py
univer_use/prompts/prompts.py
univer_use/prompts/spreadsheet_act_sysetm_prompt.md
univer_use/prompts/template.py
univer_use-0.1.2.dist-info/METADATA
univer_use-0.1.2.dist-info/WHEEL
univer_use-0.1.2.dist-info/licenses/LICENSE
univer_use-0.1.2.dist-info/RECORD
