Metadata-Version: 2.4
Name: univer-use
Version: 0.1.2
Summary: Univer Use: LangGraph-powered agent utilities and tools for Univer spreadsheets
Project-URL: Homepage, https://github.com/dream-num/univer-use
Project-URL: Repository, https://github.com/dream-num/univer-use
Project-URL: Issues, https://github.com/dream-num/univer-use/issues
Author: Univer Team
License: MIT License
License-File: LICENSE
Keywords: agents,langchain,langgraph,mcp,spreadsheets,univer
Classifier: License :: OSI Approved :: MIT License
Classifier: Operating System :: OS Independent
Classifier: Programming Language :: Python :: 3
Classifier: Programming Language :: Python :: 3.11
Classifier: Programming Language :: Python :: 3.12
Classifier: Topic :: Software Development :: Libraries
Requires-Python: <4.0,>=3.11
Requires-Dist: jinja2>=3.1.6
Requires-Dist: langchain-core>=0.3.76
Requires-Dist: langchain-mcp-adapters>=0.1.10
Requires-Dist: langchain-openai<0.4.0,>=0.3.33
Requires-Dist: langchain==0.3.27
Requires-Dist: langgraph==0.6.6
Requires-Dist: python-dotenv>=1.0.0
